TOPSIS_package/cli.py
topsis_Bhavya-1.0.0.dist-info/LICENCE
topsis_Bhavya-1.0.0.dist-info/METADATA
topsis_Bhavya-1.0.0.dist-info/WHEEL
topsis_Bhavya-1.0.0.dist-info/entry_points.txt
topsis_Bhavya-1.0.0.dist-info/top_level.txt
topsis_Bhavya-1.0.0.dist-info/RECORD
