Metadata-Version: 2.1
Name: topsis-Bhavya
Version: 1.0.0
Summary: Topsis analysis of a csv file
Home-page: UNKNOWN
Author: Bhavya
Author-email: aldbhavyagupta@gmail.com
License: MIT
Platform: UNKNOWN
Classifier: License :: OSI Approved :: MIT License
Classifier: Programming Language :: Python :: 3
Classifier: Programming Language :: Python :: 3.7
Requires-Dist: numpy
Requires-Dist: pandas
